starmart/__init__.py
starmart/__main__.py
starmart/helper.py
starmart/input.py
starmart/result.py
starmart/config/__init__.py
starmart/config/config.py
starmart/config/production_config.py
starmart-0.2.10.data/scripts/starmart
starmart-0.2.10.dist-info/LICENSE
starmart-0.2.10.dist-info/METADATA
starmart-0.2.10.dist-info/WHEEL
starmart-0.2.10.dist-info/top_level.txt
starmart-0.2.10.dist-info/RECORD
