Metadata-Version: 2.1
Name: starmart
Version: 0.2.10
Summary: Starmart deployment tool
Home-page: https://starmart.io
Author: Tomas Piaggio
Author-email: tomaspiaggio@starmart.io
License: apache-2.0
Keywords: AI,Machine Learning,Deep Learning,Serverless
Platform: UNKNOWN
License-File: LICENSE
Requires-Dist: GitPython (==3.1.24)
Requires-Dist: flask (==2.0.2)
Requires-Dist: waitress (==2.0.0)
Requires-Dist: halo (==0.0.31)
Requires-Dist: cryptography (==36.0.1)
Requires-Dist: opencv-python (~=4.5.3)
Requires-Dist: numpy (==1.21.2)
Requires-Dist: flask-cors (==3.0.10)
Requires-Dist: sshconf (==0.2.2)
Requires-Dist: Pillow (==8.2.0)
